Metadata-Version: 2.1
Name: flask-change-password
Version: 0.0.7
Summary: password change and set pages for Flask.
Home-page: https://github.com/Martlark/flask-change-password
Author: Andrew Rowe
Author-email: rowe.andrew.d@gmail.com
License: Apache Software License
Download-URL: https://github.com/Martlark/flask-change-password/archive/0.0.7.tar.gz
Keywords: flask change password page
Platform: UNKNOWN
Classifier: Development Status :: 5 - Production/Stable
Classifier: Intended Audience :: Developers
Classifier: Topic :: Software Development :: Libraries :: Python Modules
Classifier: License :: OSI Approved :: Apache Software License
Classifier: Programming Language :: Python
Classifier: Programming Language :: Python :: 2
Classifier: Programming Language :: Python :: 3
Classifier: Programming Language :: Python :: 2.7
Classifier: Programming Language :: Python :: 3.4
Classifier: Programming Language :: Python :: 3.5
Classifier: Programming Language :: Python :: 3.6
Classifier: Programming Language :: Python :: 3.7
Classifier: Operating System :: POSIX
Classifier: Operating System :: MacOS
Classifier: Operating System :: Unix
Classifier: Operating System :: Microsoft :: Windows
